pythonvideoannotator_module_virtualobjectgenerator/__init__.py
pythonvideoannotator_module_virtualobjectgenerator/module.py
pythonvideoannotator_module_virtualobjectgenerator/videosexporter/__init__.py
pythonvideoannotator_module_virtualobjectgenerator/videosexporter/videosexporter_gui.py
pythonvideoannotator_module_virtualobjectgenerator/videosexporter/videosexporter_preview.py
pythonvideoannotator_module_virtualobjectgenerator/videosexporter/videosexporter_process.py
Python_video_annotator_module_virtual_object_generator-0.6.26.dist-info/METADATA
Python_video_annotator_module_virtual_object_generator-0.6.26.dist-info/WHEEL
Python_video_annotator_module_virtual_object_generator-0.6.26.dist-info/top_level.txt
Python_video_annotator_module_virtual_object_generator-0.6.26.dist-info/RECORD
