Metadata-Version: 2.1
Name: Python-video-annotator-module-virtual-object-generator
Version: 0.6.26
Summary: UNKNOWN
Home-page: https://bitbucket.org/fchampalimaud/pythonvideoannotator-module-virtualobjectgenerator
Author: ['Ricardo Ribeiro']
Author-email: ricardojvr@gmail.com
License: UNKNOWN
Platform: UNKNOWN
